{
  "strategy": "overnight_qqq_fri_skip",
  "init_capital": 100000.0,
  "cash": 101190.9927134078,
  "positions": {},
  "last_run": "2026-05-01T21:00:00",
  "pnl_cum": 1190.9927134078025,
  "pnl_history": [
    {
      "date": "2026-04-22",
      "pnl_day": -50.0,
      "eod_value": 99950.0
    },
    {
      "date": "2026-04-22",
      "pnl_day": -0.024999999994179234,
      "eod_value": 99949.975
    },
    {
      "date": "2026-04-22",
      "timestamp": "2026-04-22T21:00:00",
      "frequency": "daily",
      "pnl_day": 0.0,
      "eod_value": 99949.975
    },
    {
      "date": "2026-05-01",
      "timestamp": "2026-05-01T09:30:00",
      "frequency": "daily",
      "pnl_day": -152.1244346647727,
      "eod_value": 99797.85056533523
    },
    {
      "date": "2026-04-27",
      "timestamp": "2026-04-27T21:00:00",
      "frequency": "daily",
      "pnl_day": -49.89892528267228,
      "eod_value": 99747.95164005256
    },
    {
      "date": "2026-04-28",
      "timestamp": "2026-04-28T21:00:00",
      "frequency": "daily",
      "pnl_day": -1003.6666555546981,
      "eod_value": 98744.28498449786
    },
    {
      "date": "2026-04-29",
      "timestamp": "2026-04-29T21:00:00",
      "frequency": "daily",
      "pnl_day": 603.6865058224503,
      "eod_value": 99347.97149032031
    },
    {
      "date": "2026-04-30",
      "timestamp": "2026-04-30T21:00:00",
      "frequency": "daily",
      "pnl_day": 926.5465988564974,
      "eod_value": 100274.51808917681
    },
    {
      "date": "2026-05-01",
      "timestamp": "2026-05-01T21:00:00",
      "frequency": "daily",
      "pnl_day": 916.474624230992,
      "eod_value": 101190.9927134078
    }
  ],
  "strategy_meta": {}
}